json_cooker/base.py
json_cooker/utils.py
enka_rs_assets-0.1.0.dist-info/METADATA
enka_rs_assets-0.1.0.dist-info/WHEEL
enka_rs_assets-0.1.0.dist-info/top_level.txt
enka_rs_assets-0.1.0.dist-info/RECORD
